qwen_payslip_processor/__init__.py
qwen_payslip_processor/config_defaults.py
qwen_payslip_processor/processor.py
qwen_payslip_processor/utils.py
qwen_payslip_processor/model_files/MODEL_READY
qwen_payslip_processor-0.1.4.dist-info/licenses/LICENSE
qwen_payslip_processor-0.1.4.dist-info/METADATA
qwen_payslip_processor-0.1.4.dist-info/WHEEL
qwen_payslip_processor-0.1.4.dist-info/top_level.txt
qwen_payslip_processor-0.1.4.dist-info/RECORD
