Metadata-Version: 2.4
Name: qwen-payslip-processor
Version: 0.1.4
Summary: German payslip processor using Qwen2.5-VL-7B model
Home-page: https://github.com/calvinsendawula/qwen-payslip-processor
Author: Calvin Sendawula
Author-email: calvinsendawula188@gmail.com
Classifier: Programming Language :: Python :: 3
Classifier: Programming Language :: Python :: 3.11
Classifier: License :: OSI Approved :: MIT License
Classifier: Operating System :: OS Independent
Classifier: Topic :: Scientific/Engineering :: Artificial Intelligence
Classifier: Topic :: Scientific/Engineering :: Image Recognition
Requires-Python: >=3.11.5
License-File: LICENSE
Requires-Dist: torch<3.0.0,>=2.0.0
Requires-Dist: transformers<5.0.0,>=4.30.0
Requires-Dist: PyMuPDF<2.0.0,>=1.22.0
Requires-Dist: pillow<12.0.0,>=9.3.0
Requires-Dist: numpy<2.0.0,>=1.24.0
Requires-Dist: pyyaml<7.0.0,>=6.0
Requires-Dist: matplotlib<4.0.0,>=3.5.0
Requires-Dist: requests<3.0.0,>=2.32.0
Dynamic: author
Dynamic: author-email
Dynamic: classifier
Dynamic: description
Dynamic: description-content-type
Dynamic: home-page
Dynamic: license-file
Dynamic: requires-dist
Dynamic: requires-python
Dynamic: summary
